setup.py
pyBuildWeb/__init__.py
pyBuildWeb/build.py
pyBuildWeb/buildweb.py
pyBuildWeb.egg-info/PKG-INFO
pyBuildWeb.egg-info/SOURCES.txt
pyBuildWeb.egg-info/dependency_links.txt
pyBuildWeb.egg-info/not-zip-safe
pyBuildWeb.egg-info/requires.txt
pyBuildWeb.egg-info/top_level.txt
pyBuildWeb/_utils/__init__.py
pyBuildWeb/_utils/exceptions.py
pyBuildWeb/_utils/jsonutils.py