Metadata-Version: 1.1
Name: pyBuildWeb
Version: 0.1
Summary: BuildWeb helper service.
Home-page: https://github.com/rocky1109/pyBuildWeb
Author: Rocky Ramchandani
Author-email: riverdale1109@gmail.com
License: Apache 2.0
Keywords: vmware devops buildweb
Platform: UNKNOWN
Classifier: Development Status :: 5 - Production/Stable
Classifier: Intended Audience :: Developers
Classifier: Natural Language :: English
Classifier: License :: OSI Approved :: Apache Software License
Classifier: Programming Language :: Python
Classifier: Programming Language :: Python :: 2.6
Classifier: Programming Language :: Python :: 2.7
Classifier: Programming Language :: Python :: 3
Classifier: Programming Language :: Python :: 3.3
Classifier: Programming Language :: Python :: 3.4
Classifier: Programming Language :: Python :: 3.5
Classifier: Programming Language :: Python :: 3.6
Classifier: Programming Language :: Python :: Implementation :: CPython
Classifier: Programming Language :: Python :: Implementation :: PyPy
